schedule/__init__.py
schedule/calendars.py
schedule/cli.py
schedule/crawler.py
schedule/schedule.py
UETSchedule-0.1.5.dist-info/LICENSE.md
UETSchedule-0.1.5.dist-info/METADATA
UETSchedule-0.1.5.dist-info/WHEEL
UETSchedule-0.1.5.dist-info/entry_points.txt
UETSchedule-0.1.5.dist-info/top_level.txt
UETSchedule-0.1.5.dist-info/RECORD
